LICENSE
MANIFEST.in
README.md
lgpl-3.0.txt
setup.cfg
setup.py
python/josephine/__init__.py
python/josephine/gui.py
python/josephine.egg-info/PKG-INFO
python/josephine.egg-info/SOURCES.txt
python/josephine.egg-info/dependency_links.txt
python/josephine.egg-info/requires.txt
python/josephine.egg-info/top_level.txt
python/josephine/flow/__init__.py
python/josephine/flow/custom_home.py
python/josephine/flow/josephine_project/__init__.py
python/josephine/lib/__init__.py
python/josephine/lib/packman/__init__.py
python/josephine/lib/packman/exceptions.py
python/josephine/lib/packman/package.py
python/josephine/lib/packman/test.py